Metadata-Version: 2.1
Name: rocketmq-wise
Version: 2.0.1
Summary: RocketMQ Python Client wise lib
Author: apache.rocketmq
Author-email: dev@rocketmq.apache.org
Keywords: rocketmq
Classifier: Operating System :: MacOS
Classifier: Operating System :: POSIX
Classifier: Operating System :: POSIX :: Linux
Classifier: Programming Language :: Python
Classifier: Programming Language :: Python :: 2.7
Classifier: Programming Language :: Python :: 3.5
Classifier: Programming Language :: Python :: 3.6
Classifier: Programming Language :: Python :: 3.7
Classifier: Programming Language :: Python :: Implementation :: CPython
License-File: LICENSE
License-File: NOTICE
Requires-Dist: enum34; python_version <= "3.4"
Requires-Dist: wheel==0.37.1
